{
  "citations": [
    {
      "citation": "Bizzarement dans ce monde, ce qui ont la force de rivaliser avec les titans ont le choix de s'en éloigner.",
      "auteur": "Levi Ackerman"
    },
    {
      "citation": "L'homme ne peut échapper à la mort... Pour autant, doit-on se convaincre que la vie ne vaut rien ?",
      "auteur": "Erwin Smith"
    },
    {
      "citation": "Les conflits s'arrêteront sûrement le jour où il ne restezra polus qu'un seul représentant de notre espèce.",
      "auteur": "Erwin Smith"
    },
    {
      "citation": "On a beau être persuadé d'agir pour la bonne cause, il suffit que les temps changent pour se retrouver à l'ombre...",
      "auteur": "Hansu Zoe"
    },
    {
      "citation": "Les gens qui sont capables de changer les choses sont ceux capables de sacrifices important. Ceux qui, face à une monstre, vont même jusqu'a sacrifier leur humanité.",
      "auteur": "Armin Arlelt"
    },
    {
      "citation": "Si tu gagnes, tu vis. Si tu perds, tu meurs. Si tu ne te bats pas, Tu ne peux pas gagner.",
      "auteur": "Eren Jaeger"
    }
  ]
}
